<?xml version="1.0" encoding="UTF-8" standalone="no"?>
<Skiped_Image_Alt_UrlURLs>
                    
    
    
    
    <Skiped_Image_Alt_Url>
                                        
        
        
        
        <url>https://www.angloamericangroupfoundation.org/</url>
                                        
        
        
        
        <time>2023-04-26 06:58:12</time>
                                    
    
    
    
    </Skiped_Image_Alt_Url>
                
    
    
    
    <Skiped_Image_Alt_Url>
                                
        
        
        <url>https://www.angloamericangroupfoundation.org/where-we-work</url>
                                
        
        
        <time>2023-04-26 07:21:01</time>
                            
    
    
    </Skiped_Image_Alt_Url>
            
    
    
    <Skiped_Image_Alt_Url>
                        
        
        <url>https://www.angloamericangroupfoundation.org/where-we-work</url>
                        
        
        <time>2023-04-26 07:29:27</time>
                    
    
    </Skiped_Image_Alt_Url>
        
    
    <Skiped_Image_Alt_Url>
                
        <url>https://www.angloamericangroupfoundation.org/</url>
                
        <time>2023-04-26 08:39:40</time>
            
    </Skiped_Image_Alt_Url>
    
    <Skiped_Image_Alt_Url>
        <url>https://www.thapatechnical.com/</url>
        <time>2023-04-26 14:14:42</time>
    </Skiped_Image_Alt_Url>
</Skiped_Image_Alt_UrlURLs>
